sparseconverter/__init__.py
sparseconverter-0.5.0.dist-info/licenses/LICENSE
sparseconverter-0.5.0.dist-info/METADATA
sparseconverter-0.5.0.dist-info/WHEEL
sparseconverter-0.5.0.dist-info/top_level.txt
sparseconverter-0.5.0.dist-info/RECORD
