Metadata-Version: 2.4
Name: sparseconverter
Version: 0.5.0
Summary: Converter matrix and type determination for a range of array formats, focusing on sparse arrays
Author-email: Dieter Weber <d.weber@fz-juelich.de>
License: MIT License
Project-URL: repository, https://github.com/LiberTEM/sparseconverter
Keywords: numpy,scipy.sparse,sparse,array,matrix,cupy,cupyx.scipy.sparse
Classifier: Programming Language :: Python :: 3
Classifier: Programming Language :: Python :: 3.9
Classifier: Programming Language :: Python :: 3.10
Classifier: Programming Language :: Python :: 3.11
Classifier: Programming Language :: Python :: 3.12
Classifier: Programming Language :: Python :: 3.13
Classifier: Development Status :: 3 - Alpha
Requires-Python: >=3.9
License-File: LICENSE
Requires-Dist: numpy
Requires-Dist: scipy>=1.8
Requires-Dist: sparse>=0.12
Requires-Dist: typing-extensions
Provides-Extra: cupy
Requires-Dist: cupy; extra == "cupy"
Provides-Extra: test
Requires-Dist: pytest; extra == "test"
Requires-Dist: pytest-cov; extra == "test"
Dynamic: license-file
